{
  "_class": "group",
  "do_objectID": "63B28492-4253-4712-AE06-5874BE7108C2",
  "exportOptions": {
    "_class": "exportOptions",
    "exportFormats": [
    ],
    "includedLayerIds": [
    ],
    "layerOptions": 0,
    "shouldTrim": false
  },
  "frame": {
    "_class": "rect",
    "constrainProportions": false,
    "height": 69,
    "width": 295,
    "x": 24,
    "y": 6
  },
  "hasClickThrough": false,
  "isFlippedHorizontal": false,
  "isFlippedVertical": false,
  "isLocked": false,
  "isVisible": true,
  "layerListExpandedType": 0,
  "layers": [
    {
      "class": "text",
      "id": "036EF10B-BBC8-459B-9E3E-DF44208CE4AD"
    },
    {
      "class": "text",
      "id": "871ABBB9-EC47-4A89-B68F-28B8E5344970"
    }
  ],
  "name": "main Title",
  "nameIsFixed": true,
  "resizingConstraint": 63,
  "resizingType": 0,
  "rotation": 0,
  "shouldBreakMaskChain": false,
  "style": {
    "_class": "style",
    "endDecorationType": 0,
    "miterLimit": 10,
    "startDecorationType": 0
  }
}